setup.py
ALust_probability/Binomialdistribution.py
ALust_probability/Gaussiandistribution.py
ALust_probability/Generaldistribution.py
ALust_probability/__init__.py
ALust_probability.egg-info/PKG-INFO
ALust_probability.egg-info/SOURCES.txt
ALust_probability.egg-info/dependency_links.txt
ALust_probability.egg-info/not-zip-safe
ALust_probability.egg-info/top_level.txt