Metadata-Version: 1.0
Name: ALust-probability
Version: 0.1
Summary: Gaussian & Binomial distributions
Home-page: UNKNOWN
Author: ['Arthur Lustman']
Author-email: UNKNOWN
License: UNKNOWN
Platform: UNKNOWN
